tryp/__init__.py
tryp/either.py
tryp/list.py
tryp/map.py
tryp/maybe.py
tryp-1.0.1.dist-info/DESCRIPTION.rst
tryp-1.0.1.dist-info/METADATA
tryp-1.0.1.dist-info/RECORD
tryp-1.0.1.dist-info/WHEEL
tryp-1.0.1.dist-info/metadata.json
tryp-1.0.1.dist-info/top_level.txt
