Metadata-Version: 2.0
Name: tryp
Version: 1.0.1
Summary: tryp tools
Home-page: https://github.com/tek/tryp
Author: Torsten Schmits
Author-email: torstenschmits@gmail.com
License: MIT
Platform: UNKNOWN
Requires-Dist: fn
Requires-Dist: tek
Requires-Dist: toolz
